keyutils/_keyutils.cpython-38-x86_64-linux-gnu.so
keyutils/__init__.py
turkeyutils.libs/libkeyutils-2777d33d.so.1.6
turkeyutils-0.6.1.dist-info/top_level.txt
turkeyutils-0.6.1.dist-info/RECORD
turkeyutils-0.6.1.dist-info/WHEEL
turkeyutils-0.6.1.dist-info/METADATA
turkeyutils-0.6.1.dist-info/AUTHORS
turkeyutils-0.6.1.dist-info/LICENSE
