Metadata-Version: 2.1
Name: turkeyutils
Version: 0.6.1
Summary: keyutils bindings for Python
Home-page: https://github.com/lilatomic/turkeyutils
Author: Daniel Goldman
Author-email: danielgoldman4@gmail.com
License: Apache 2.0
Platform: Linux
Classifier: Topic :: Security
Classifier: Operating System :: POSIX :: Linux
Classifier: Programming Language :: Python :: 3.8
Classifier: Programming Language :: Python :: 3.9
Classifier: Programming Language :: Python :: 3.10
Classifier: Programming Language :: Python :: 3.11
Classifier: Programming Language :: Python :: 3.12
License-File: LICENSE
License-File: AUTHORS
